sid_kemendesa/__init__.py
sid_kemendesa/constants.py
sid_kemendesa/desa.py
sid_kemendesa/deskripsi.py
sid_kemendesa/error.py
sid_kemendesa/idm/__init__.py
sid_kemendesa/idm/idm.py
sid_kemendesa/idm/indikator.py
sid_kemendesa/idm/jenis.py
sid_kemendesa/idm/status.py
sid_kemendesa/search.py
sid_kemendesa-0.2.0.dist-info/LICENSE
sid_kemendesa-0.2.0.dist-info/WHEEL
sid_kemendesa-0.2.0.dist-info/METADATA
sid_kemendesa-0.2.0.dist-info/RECORD
