Metadata-Version: 2.1
Name: sid-kemendesa
Version: 0.2.0
Summary: Module python untuk mencari dan melihat data desa dari sid kemendesa.
Keywords: sid-desa,kemendesa,python-module,python-sdk,python-wrapper
Author: hexatester
Author-email: hexatester@protonmail.com
Requires-Python: >=3.7,<4.0
Classifier: Development Status :: 4 - Beta
Classifier: Intended Audience :: Developers
Classifier: License :: OSI Approved :: GNU General Public License v3 (GPLv3)
Classifier: Operating System :: OS Independent
Classifier: Programming Language :: Python :: 3
Classifier: Programming Language :: Python :: 3.7
Classifier: Programming Language :: Python :: 3.8
Classifier: Programming Language :: Python :: 3.9
Requires-Dist: attrs (>=20.3.0,<21.0.0)
Requires-Dist: beautifulsoup4 (>=4.9.3,<5.0.0)
Requires-Dist: cattrs (>=1.6.0,<2.0.0)
Requires-Dist: requests (>=2.25.1,<3.0.0)
